dsmde/__init__.py
dsmde-0.1.dist-info/LICENSE
dsmde-0.1.dist-info/METADATA
dsmde-0.1.dist-info/WHEEL
dsmde-0.1.dist-info/top_level.txt
dsmde-0.1.dist-info/RECORD
