Metadata-Version: 2.1
Name: dsmde
Version: 0.1
License-File: LICENSE
Requires-Dist: requests
Requires-Dist: pandas
